__main__.py
xdcs/__init__.py
xdcs/agent_cli.py
xdcs/app.py
xdcs/config.py
xdcs/decorators.py
xdcs/docker.py
xdcs/gpu.py
xdcs/object_repository.py
xdcs/parameters.py
xdcs/xdcs.py
xdcs/cmd/__init__.py
xdcs/cmd/object_repository.py
xdcs/cmd/registration.py
xdcs/cmd/tasks.py
xdcs/conf/xdcs-agent.toml
xdcs_agent-0.1.0.dev20191125215215.dist-info/METADATA
xdcs_agent-0.1.0.dev20191125215215.dist-info/WHEEL
xdcs_agent-0.1.0.dev20191125215215.dist-info/entry_points.txt
xdcs_agent-0.1.0.dev20191125215215.dist-info/namespace_packages.txt
xdcs_agent-0.1.0.dev20191125215215.dist-info/top_level.txt
xdcs_agent-0.1.0.dev20191125215215.dist-info/zip-safe
xdcs_agent-0.1.0.dev20191125215215.dist-info/RECORD
